amazonian/S3.py
amazonian/S3File.py
amazonian/__init__.py
amazonian/redshift/BasicRedshift.py
amazonian/redshift/Column.py
amazonian/redshift/Metadata.py
amazonian/redshift/Redshift.py
amazonian/redshift/Schema.py
amazonian/redshift/Snapshot.py
amazonian/redshift/Table.py
amazonian/redshift/__init__.py
amazonian/redshift/get_redshift_create_table_query.py
amazonian-2022.5.27.dist-info/LICENSE
amazonian-2022.5.27.dist-info/METADATA
amazonian-2022.5.27.dist-info/WHEEL
amazonian-2022.5.27.dist-info/top_level.txt
amazonian-2022.5.27.dist-info/RECORD
