Metadata-Version: 2.1
Name: amazonian
Version: 2022.5.27
Summary: Python library for working with Amazon Web Services such as Redshift and S3
Home-page: https://github.com/idin/amazonian
Author: Idin
Author-email: py@idin.ca
License: MIT
Platform: UNKNOWN
Classifier: Development Status :: 3 - Alpha
Classifier: Intended Audience :: Developers
Classifier: Programming Language :: Python :: 3 :: Only
Classifier: Programming Language :: Python :: 3.6
Classifier: Programming Language :: Python :: 3.7
Classifier: Topic :: Software Development :: Libraries :: Python Modules
Requires-Python: ~=3.6
Requires-Dist: numpy
Requires-Dist: pandas
Requires-Dist: sqlalchemy
Requires-Dist: psycopg2-binary
Requires-Dist: s3fs (>=2022.2.0)
Requires-Dist: urllib3 (>=1.26.8)
